{"cases": [{"label": "事件订阅 Webhook", "status": "PENDING", "apiName": "", "caseKey": "webhook_challenge", "success": "", "required": false, "requestId": "", "latestTime": "", "nextAction": "开放平台连接测试已由 preflight 覆盖；真实事件会写同步日志", "logidSource": "X-Bytedance-Logid 或 challenge", "errorMessage": ""}, {"label": "三方码发券 SPI", "status": "PENDING", "apiName": "", "caseKey": "issue_code", "success": "", "required": true, "requestId": "", "latestTime": "", "nextAction": "用真实下单触发发券，复制 logid 到开放平台", "logidSource": "请求头 X-Bytedance-Logid", "errorMessage": ""}, {"label": "预约创单/支付回调", "status": "PENDING", "apiName": "", "caseKey": "reservation_callback", "success": "", "required": true, "requestId": "", "latestTime": "", "nextAction": "用户真实预约或支付后，等待抖音推送 order-create/pay-notify", "logidSource": "请求头 X-Bytedance-Logid", "errorMessage": ""}, {"label": "接单 OpenAPI", "status": "PENDING", "apiName": "", "caseKey": "confirm_order", "success": "", "required": true, "requestId": "", "latestTime": "", "nextAction": "拿真实 book_id 调用接单；若创单已同步确认，记录平台说明", "logidSource": "响应 extra.logid 或 logid", "errorMessage": ""}, {"label": "整单核销 OpenAPI", "status": "PENDING", "apiName": "", "caseKey": "verify_order", "success": "", "required": true, "requestId": "", "latestTime": "", "nextAction": "拿真实券码或 verify_token 调用核销", "logidSource": "响应 extra.logid 或 logid", "errorMessage": ""}, {"label": "订单自动/补偿同步", "status": "FAILED", "apiName": "life_order_auto_sync", "caseKey": "order_auto_sync", "success": "0", "required": false, "requestId": "2026061610583174D2AF72DA7A28148929", "latestTime": "2026-06-16 10:58:35", "nextAction": "自动同步或手动同步用于补偿漏推订单", "logidSource": "响应 extra.logid 或 logid", "errorMessage": "同步已停止：达到订单总数安全上限 maxTotal=80，请检查查询时间范围或抖音订单查询返回"}, {"label": "退款通知/申请", "status": "PASS", "apiName": "refund_notify", "caseKey": "refund_flow", "success": "1", "required": false, "requestId": "02178097981027600000000000000000000ffff0ad4bd17998162", "latestTime": "2026-06-09 12:36:50", "nextAction": "退款用例需要时再填对应 logid", "logidSource": "请求头 X-Bytedance-Logid", "errorMessage": ""}], "status": "PENDING_EXTERNAL_ACCEPTANCE", "channel": "DOUYIN_LIFE", "caseCounts": {"failed": 0, "passed": 0, "pending": 4, "required": 4}, "eventInbox": {"dead": 0, "done": 0, "retry": 0, "total": 2, "failed": 2, "status": "WARNING", "retryable": 2, "latestEventTime": "2026-06-13 16:52:53"}, "generatedAt": "2026-06-16 03:01:58 +00:00", "windowHours": 168, "latestEvents": [{"eventType": "LIFE_ORDER_QUERY", "requestId": "", "createTime": "2026-06-13 16:52:53", "processStatus": "FAILED", "maskedExternalOrderId": ""}, {"eventType": "LIFE_ORDER_QUERY", "requestId": "", "createTime": "2026-06-13 16:50:33", "processStatus": "FAILED", "maskedExternalOrderId": ""}]}